{
  "id": "first_year",
  "type": "SharedSlice",
  "name": "FirstYear",
  "description": "FirstYear",
  "variations": [
    {
      "id": "default",
      "name": "Default",
      "docURL": "...",
      "version": "sktwi1xtmkfgx8626",
      "description": "FirstYear",
      "primary": {
        "meses": {
          "type": "StructuredText",
          "config": {
            "label": "meses",
            "placeholder": "A nice description of your product",
            "allowTargetBlank": true,
            "single": "paragraph"
          }
        }
      },
      "items": {},
      "imageUrl": "https://images.prismic.io/slice-machine/621a5ec4-0387-4bc5-9860-2dd46cbc07cd_default_ss.png?auto=compress,format"
    }
  ]
}